mst/simplerpc/__init__.py
mst/simplerpc/simplerpc.py
mst_simplerpc-1.2.0.dist-info/METADATA
mst_simplerpc-1.2.0.dist-info/WHEEL
mst_simplerpc-1.2.0.dist-info/top_level.txt
mst_simplerpc-1.2.0.dist-info/RECORD
