Metadata-Version: 2.1
Name: mst-simplerpc
Version: 1.2.0
Summary: Used to access Missouri S&T IT's simplified RPC implementation
Author-email: Missouri University of Science and Technology - Information Technology <it-ai@mst.edu>
Requires-Python: >=3.8
Requires-Dist: requests
Requires-Dist: mst-core
Requires-Dist: mst-authsrv
